__init__.py
_version.py
fibphoflow.py
fibphoflow-0.1.8.dist-info/LICENSE
fibphoflow-0.1.8.dist-info/METADATA
fibphoflow-0.1.8.dist-info/WHEEL
fibphoflow-0.1.8.dist-info/top_level.txt
fibphoflow-0.1.8.dist-info/RECORD
