Metadata-Version: 2.1
Name: fibphoflow
Version: 0.1.8
Summary: Python package to process and visualize TDT fiber photometry data
License: MIT License
Keywords: neuroscience,calcium activity,fiber photometry,data processing
Classifier: Intended Audience :: Science/Research
Classifier: Natural Language :: English
Classifier: Operating System :: OS Independent
Classifier: Programming Language :: Python
Classifier: Topic :: Scientific/Engineering
License-File: LICENSE
Requires-Dist: numpy
Requires-Dist: pandas
Requires-Dist: seaborn
Requires-Dist: scipy
Requires-Dist: tables
Requires-Dist: tdt
Requires-Dist: xlsxwriter
Requires-Dist: importlib-metadata ; python_version < "3.8"
